plone.cachepurging-3.0.3-py3.13-nspkg.pth
plone/cachepurging/__init__.py
plone/cachepurging/browser.py
plone/cachepurging/configure.zcml
plone/cachepurging/hooks.py
plone/cachepurging/interfaces.py
plone/cachepurging/paths.py
plone/cachepurging/purger.py
plone/cachepurging/rewrite.py
plone/cachepurging/utils.py
plone/cachepurging/tests/__init__.py
plone/cachepurging/tests/test_hooks.py
plone/cachepurging/tests/test_purger.py
plone/cachepurging/tests/test_rewrite.py
plone/cachepurging/tests/test_traversable_paths.py
plone/cachepurging/tests/test_utils.py
plone/cachepurging/tests/test_views.py
plone_cachepurging-3.0.3.dist-info/METADATA
plone_cachepurging-3.0.3.dist-info/WHEEL
plone_cachepurging-3.0.3.dist-info/namespace_packages.txt
plone_cachepurging-3.0.3.dist-info/top_level.txt
plone_cachepurging-3.0.3.dist-info/RECORD
